transmute/__init__.py
transmute/cli.py
transmute/converter.py
transmute/core/__init__.py
transmute/core/enums.py
transmute/core/exceptions.py
transmute/core/models.py
transmute/formats/__init__.py
transmute/formats/archidekt.py
transmute/formats/base.py
transmute/formats/cardkingdom.py
transmute/formats/cardsphere.py
transmute/formats/deckbox.py
transmute/formats/deckbuilder.py
transmute/formats/deckstats.py
transmute/formats/dragonshield.py
transmute/formats/helvault.py
transmute/formats/manabox.py
transmute/formats/moxfield.py
transmute/formats/mtggoldfish.py
transmute/formats/mtgmanager.py
transmute/formats/mtgo.py
transmute/formats/mtgstocks.py
transmute/formats/mtgstudio.py
transmute/formats/tcgplayer.py
transmute/scryfall/__init__.py
transmute/scryfall/api.py
transmute/scryfall/enrichment.py
transmute_mtg-0.1.0.dist-info/METADATA
transmute_mtg-0.1.0.dist-info/WHEEL
transmute_mtg-0.1.0.dist-info/entry_points.txt
transmute_mtg-0.1.0.dist-info/licenses/LICENSE
transmute_mtg-0.1.0.dist-info/RECORD
