Metadata-Version: 2.4
Name: transmute-mtg
Version: 0.1.0
Summary: CLI tool for converting MTG collection CSV files between formats
Project-URL: Homepage, https://github.com/oflannabhra/transmute
Project-URL: Repository, https://github.com/oflannabhra/transmute
Project-URL: Issues, https://github.com/oflannabhra/transmute/issues
Author-email: Ben Flannery <oflannabhra@gmail.com>
License-Expression: MIT
License-File: LICENSE
Keywords: collection,converter,csv,deckbox,dragonshield,magic,magic-the-gathering,manabox,moxfield,mtg,scryfall,tcgplayer
Classifier: Development Status :: 4 - Beta
Classifier: Environment :: Console
Classifier: Intended Audience :: End Users/Desktop
Classifier: License :: OSI Approved :: MIT License
Classifier: Operating System :: OS Independent
Classifier: Programming Language :: Python :: 3
Classifier: Programming Language :: Python :: 3.12
Classifier: Topic :: Games/Entertainment
Classifier: Topic :: Utilities
Classifier: Typing :: Typed
Requires-Python: >=3.12
Requires-Dist: click>=8.0
Requires-Dist: requests>=2.28
Requires-Dist: rich>=13.0
